MANIFEST.in
README
setup.py
beatle/__init__.py
beatle/start.py
beatle.egg-info/PKG-INFO
beatle.egg-info/SOURCES.txt
beatle.egg-info/dependency_links.txt
beatle.egg-info/requires.txt
beatle.egg-info/top_level.txt
beatle/activity/__init__.py
beatle/activity/arch/__init__.py
beatle/activity/arch/actions/__init__.py
beatle/activity/arch/actions/build.py
beatle/activity/arch/actions/debug.py
beatle/activity/arch/handlers/__init__.py
beatle/activity/arch/handlers/cpp/EditorHandler.py
beatle/activity/arch/handlers/cpp/__init__.py
beatle/activity/arch/handlers/py/EditorHandler.py
beatle/activity/arch/handlers/py/__init__.py
beatle/activity/arch/handlers/text/EditorHandler.py
beatle/activity/arch/handlers/text/__init__.py
beatle/activity/arch/ui/__init__.py
beatle/activity/arch/ui/ui.py
beatle/activity/arch/ui/dlg/NewDir.py
beatle/activity/arch/ui/dlg/NewFile.py
beatle/activity/arch/ui/dlg/__init__.py
beatle/activity/arch/ui/pane/Breakpoints.py
beatle/activity/arch/ui/pane/DebugCommand.py
beatle/activity/arch/ui/pane/Expressions.py
beatle/activity/arch/ui/pane/FilePane.py
beatle/activity/arch/ui/pane/FilePythonPane.py
beatle/activity/arch/ui/pane/Locals.py
beatle/activity/arch/ui/pane/StackFrame.py
beatle/activity/arch/ui/pane/TextPane.py
beatle/activity/arch/ui/pane/Threads.py
beatle/activity/arch/ui/pane/__init__.py
beatle/activity/arch/ui/view/FilesView.py
beatle/activity/arch/ui/view/__init__.py
beatle/activity/git/__init__.py
beatle/activity/git/ui/__init__.py
beatle/activity/git/ui/ui.py
beatle/activity/git/ui/dlg/CommitGit.py
beatle/activity/git/ui/dlg/GitRemote.py
beatle/activity/git/ui/dlg/GitRepo.py
beatle/activity/git/ui/dlg/OpenGitRepo.py
beatle/activity/git/ui/dlg/Progress.py
beatle/activity/git/ui/dlg/__init__.py
beatle/activity/git/ui/view/GitView.py
beatle/activity/git/ui/view/__init__.py
beatle/activity/models/__init__.py
beatle/activity/models/handlers/__init__.py
beatle/activity/models/handlers/cpp/EditorHandler.py
beatle/activity/models/handlers/cpp/__init__.py
beatle/activity/models/handlers/gui/__init__.py
beatle/activity/models/handlers/py/EditorHandler.py
