Metadata-Version: 1.1
Name: beatle
Version: 0.2.4
Summary: A development environment made in python
Home-page: https://github.com/melviso/beatle
Author: mel viso
Author-email: melviso@telefonica.net
License: GNU Public License
Keywords: development python c++
Platform: UNKNOWN
Classifier: Intended Audience :: Developers
Classifier: Development Status :: 2 - Pre-Alpha
Classifier: Topic :: Utilities
Classifier: License :: OSI Approved :: GNU General Public License (GPL)
Classifier: Natural Language :: English
Classifier: Operating System :: POSIX :: Linux
Classifier: Programming Language :: Python :: 2.7
Classifier: Topic :: Software Development :: Code Generators
